nano_banana.py
figmaker-1.3.0.dist-info/licenses/LICENSE
figmaker-1.3.0.dist-info/METADATA
figmaker-1.3.0.dist-info/WHEEL
figmaker-1.3.0.dist-info/entry_points.txt
figmaker-1.3.0.dist-info/top_level.txt
figmaker-1.3.0.dist-info/RECORD
