Metadata-Version: 2.4
Name: figmaker
Version: 1.3.0
Summary: AI-powered image generation and editing CLI tool using Gemini Nano Banana API
Home-page: https://github.com/yourusername/figmaker
Author: FigMaker
Author-email: 
License: MIT
Project-URL: Homepage, https://github.com/yourusername/figmaker
Project-URL: Issues, https://github.com/yourusername/figmaker/issues
Keywords: ai,image,generation,editing,gemini,cli
Classifier: Development Status :: 4 - Beta
Classifier: Intended Audience :: Developers
Classifier: Topic :: Multimedia :: Graphics
Classifier: License :: OSI Approved :: MIT License
Classifier: Programming Language :: Python :: 3
Classifier: Programming Language :: Python :: 3.8
Classifier: Programming Language :: Python :: 3.9
Classifier: Programming Language :: Python :: 3.10
Classifier: Programming Language :: Python :: 3.11
Classifier: Programming Language :: Python :: 3.12
Classifier: Programming Language :: Python :: 3.13
Requires-Python: >=3.8
License-File: LICENSE
Requires-Dist: google-genai>=1.45.0
Requires-Dist: pillow>=12.0.0
Dynamic: home-page
Dynamic: license-file
Dynamic: requires-python
